{
  "us_m1a1_abrams": {
    "name": "M1A1 艾布拉姆斯主战坦克",
    "class_type": "mbt",
    "visuals": {
      "icon": "icon_mbt_blue",
      "model_scale": 1.0
    },
    "combat_stats": {
      "max_hp": 12,
      "attack": 3.0,
      "defense": 2.5
    },
    "system_vars": {
      "cost": 275,
      "base_weight": 10
    },
    "tactical_tags": {
      "domain": "Ground",
      "capabilities": ["HeavyAntiTank", "HeavyArmor"]
    }

  },

"us_m1a1_acav": {
    "name": "M1A1 ACAV 侦察主战坦克",
    "class_type": "mbt",
    "visuals": {
      "icon": "icon_mbt_blue",
      "model_scale": 1.0
    },
    "combat_stats": {
      "max_hp": 12,
      "attack": 3.1,
      "defense": 2.7
    },
    "system_vars": {
      "cost": 290,
      "base_weight": 4
    },
    "tactical_tags": {
      "domain": "Rear",
      "capabilities": ["HeavyAntiTank", "HeavyArmor", "Recon"]
    }
  },

  "us_m1a1_abrams_cp": {
    "name": "M1A1 艾布拉姆斯主战坦克（指挥车版）",
    "class_type": "mbt",
    "visuals": {
      "icon": "icon_mbt_blue",
      "model_scale": 1.0
    },
    "combat_stats": {
      "max_hp": 12,
      "attack": 3.0,
      "defense": 2.5
    },
    "system_vars": {
      "cost": 315,
      "base_weight": 4
    },
    "tactical_tags": {
      "domain": "Rear",
      "capabilities": ["HeavyAntiTank", "HeavyArmor", "Command"]
    }

  },

  "us_m2a2_bradley": {
    "name": "M2A2 布雷德利步兵战车",
    "class_type": "ifv",
    "visuals": {
      "icon": "icon_ifv_blue",
      "model_scale": 1.0
    },
    "combat_stats": {
      "max_hp": 8,
      "attack": 1.7,
      "defense": 2.3
    },
    "system_vars": {
      "cost": 85,
      "base_weight": 8
    },
    "tactical_tags": {
      "domain": "Ground",
      "capabilities": ["HeavyAntiTank", "Armor"]
    }
  },



  "us_mech_rifles": {
    "name": "美军机械化步兵班",
    "class_type": "infantry",
    "visuals": {
      "icon": "icon_inf_blue",
      "model_scale": 1.0
    },
    "combat_stats": {
      "max_hp": 9,
      "attack": 1.0,
      "defense": 1.0
    },
    "system_vars": {
      "cost": 25,
      "base_weight": 10
    },
    "tactical_tags": {
      "domain": "Ground",
      "capabilities": ["LightAntiTank"]
    }
  },

  "us_ah64a_apache": {
    "name": "AH-64A 阿帕奇武装直升机",
    "class_type": "atk_heli",
    "visuals": {
      "icon": "icon_heli_blue",
      "model_scale": 1.0
    },
    "combat_stats": {
      "max_hp": 6,
      "attack": 2.5,
      "defense": 3.0
    },
    "system_vars": {
      "cost": 240,
      "base_weight": 4
    },
    "tactical_tags": {
      "domain": "Heli",
      "capabilities": ["HeavyAntiTank"]
    }
  },

  "us_m109a2": {
    "name": "M109A2 自行榴弹炮",
    "class_type": "spa_arty",
    "visuals": {
      "icon": "icon_spa_arty_blue",
      "model_scale": 1.0
    },
    "combat_stats": {
      "max_hp": 4,
      "attack": 2.0,
      "defense": 2.0
    },
    "system_vars": {
      "cost": 210,
      "base_weight": 4
    },
    "tactical_tags": {
      "domain": "Rear",
      "capabilities": [""]
    }
  },

  "us_stinger": {
    "name": "美军毒刺防空班",
    "class_type": "inf_aa",
    "visuals": {
      "icon": "icon_inf_aa_blue",
      "model_scale": 1.0
    },
    "combat_stats": {
      "max_hp": 2,
      "attack": 0.2,
      "defense": 1.0
    },
    "system_vars": {
      "cost": 50,
      "base_weight": 4
    },
    "tactical_tags": {
      "domain": "Rear",
      "capabilities": [""]
    }
  },

  "us_tow2": {
    "name": "美军TOW-2反坦克班",
    "class_type": "inf_at",
    "visuals": {
      "icon": "icon_inf_at_blue",
      "model_scale": 1.0
    },
    "combat_stats": {
      "max_hp": 2,
      "attack": 0.2,
      "defense": 1.7
    },
    "system_vars": {
      "cost": 30,
      "base_weight": 4
    },
    "tactical_tags": {
      "domain": "Rear",
      "capabilities": ["HeavyAntiTank"]
    }
  }, 

  "us_aero_rifles": {
    "name": "美军空降突击班",
    "class_type": "inf_air",
    "visuals": {
      "icon": "icon_inf_air_blue",
      "model_scale": 1.0
    },
    "combat_stats": {
      "max_hp": 9,
      "attack": 1.2,
      "defense": 1.2
    },
    "system_vars": {
      "cost": 55,
      "base_weight": 10
    },
    "tactical_tags": {
      "domain": "Ground",
      "capabilities": ["LightAntiTank"]
    }
  },

  "us_uh_60a_blackhawk": {
    "name": "UH-60A 黑鹰运输直升机",
    "class_type": "trans_heli",
    "visuals": {
      "icon": "icon_trans_heli_blue",
      "model_scale": 1.0
    },
    "combat_stats": {
      "max_hp": 2,
      "attack": 0.1,
      "defense": 0.2
    },
    "system_vars": {
      "cost": 50,
      "base_weight": 4
    },
    "tactical_tags": {
      "domain": "Heli",
      "capabilities": [""]
    }
  },

  "us_mim104": {
    "name": "MIM104 爱国者防空导弹系统",
    "class_type": "sam_stac",
    "visuals": {
      "icon": "icon_sam_stac_blue",
      "model_scale": 1.0
    },
    "combat_stats": {
      "max_hp": 4,
      "attack": 0.1,
      "defense": 0.1
    },
    "aa_area": 15,
    "system_vars": {
      "cost": 200,
      "base_weight": 4
    },
    "tactical_tags": {
      "domain": "Rear",
      "capabilities": [""]
    }
  },

  "us_i_hawk": {
    "name": "MIM23 HAWK 防空导弹系统",
    "class_type": "sam_stac",
    "visuals": {
      "icon": "icon_sam_stac_blue",
      "model_scale": 1.0
    },
    "combat_stats": {
      "max_hp": 4,
      "attack": 0.1,
      "defense": 0.1
    },
    "aa_area": 12,
    "system_vars": {
      "cost": 110,
      "base_weight": 4
    },
    "tactical_tags": {
      "domain": "Rear",
      "capabilities": [""]
    }
  }
}